[
  {
    "url": "https://github.com/TypesettingTools/CoffeeFlux-Aegisub-Scripts#Flux.Selegator",
    "author": "tophf",
    "name": "Selegator",
    "description": "Select/navigate in the subtitle grid",
    "fileBaseUrl": "https://raw.githubusercontent.com/TypesettingTools/CoffeeFlux-Aegisub-Scripts/@{channel}/macros/Flux.Selegator",
    "channels": {
      "master": {
        "version": "1.1.5",
        "released": "2016-03-22",
        "default": true,
        "files": [
          {
            "name": ".moon",
            "url": "https://raw.githubusercontent.com/TypesettingTools/CoffeeFlux-Aegisub-Scripts/master/macros/Flux.Selegator.moon",
            "sha1": "26CA040E6D2F8FA74A1282209820B99DEE2B8E01",
            "_validHash": true
          }
        ]
      }
    },
    "changelog": {
      "1.1.5": [
        "Updated to use single quotes"
      ],
      "1.1.4": [
        "Updated to reflect new directory structure"
      ],
      "1.1.3": [
        "Fixed feed error"
      ],
      "1.1.2": [
        "Removed superfluous commas"
      ],
      "1.1.1": [
        "Mild cleanup"
      ],
      "1.1.0": [
        "Added to DepCtrl"
      ]
    },
    "_validHash": true,
    "_defaultVersion": "1.1.5",
    "_scriptData": {
      "name": "Selegator",
      "description": "Select/navigate in the subtitle grid",
      "author": "tophf",
      "version": "1.1.5",
      "namespace": "Flux.Selegator",
      "_feedData": {
        "feed": "https://raw.githubusercontent.com/TypesettingTools/CoffeeFlux-Aegisub-Scripts/master/DependencyControl.json"
      }
    },
    "_feedName": "CoffeeFlux's Aegisub Scripts",
    "_feedIdentifier": "b6a37e0",
    "_fetchTime": 1670841941946,
    "_sourceUrl": "https://raw.githubusercontent.com/TypesettingTools/CoffeeFlux-Aegisub-Scripts/master/DependencyControl.json",
    "_namespace": "Flux.Selegator"
  }
]