[
  {
    "url": "https://github.com/unanimated/luaegisub#ua.Selectrix",
    "author": "unanimated",
    "name": "Selectricks",
    "description": "Selectricks and Sortricks",
    "channels": {
      "master": {
        "version": "3.4.0",
        "released": "2018-08-05",
        "default": true,
        "files": [
          {
            "name": ".lua",
            "url": "https://raw.githubusercontent.com/unanimated/luaegisub/master/ua.Selectrix.lua",
            "sha1": "ab007be53835586317f779874b1d5f3af1c3f107",
            "_validHash": true
          }
        ]
      }
    },
    "changelog": {
      "3.4.0": [
        "Check the Updates page"
      ]
    },
    "_validHash": true,
    "_defaultVersion": "3.4.0",
    "_scriptData": {
      "name": "Selectricks",
      "description": "Selectricks and Sortricks",
      "author": "unanimated",
      "version": null,
      "namespace": "ua.Selectrix",
      "_feedData": {
        "feed": "https://raw.githubusercontent.com/unanimated/luaegisub/master/DependencyControl.json"
      }
    },
    "_feedName": "unanimated's Automation Scripts",
    "_feedIdentifier": "720a751",
    "_fetchTime": 1702168251523,
    "_sourceUrl": "https://raw.githubusercontent.com/TypesettingTools/unanimated-Aegisub-Scripts/master/DependencyControl.json",
    "_namespace": "ua.Selectrix"
  },
  {
    "url": "https://github.com/unanimated/luaegisub#ua.Selectrix",
    "author": "unanimated",
    "name": "Selectricks",
    "description": "Selectricks and Sortricks",
    "channels": {
      "master": {
        "version": "3.4.0",
        "released": "2018-08-05",
        "default": true,
        "files": [
          {
            "name": ".lua",
            "url": "https://raw.githubusercontent.com/unanimated/luaegisub/master/ua.Selectrix.lua",
            "sha1": "ab007be53835586317f779874b1d5f3af1c3f107",
            "_validHash": true
          }
        ]
      }
    },
    "changelog": {
      "3.4.0": [
        "Check the Updates page"
      ]
    },
    "_validHash": true,
    "_defaultVersion": "3.4.0",
    "_scriptData": {
      "name": "Selectricks",
      "description": "Selectricks and Sortricks",
      "author": "unanimated",
      "version": null,
      "namespace": "ua.Selectrix",
      "_feedData": {
        "feed": "https://raw.githubusercontent.com/unanimated/luaegisub/master/DependencyControl.json"
      }
    },
    "_feedName": "unanimated's Automation Scripts",
    "_feedIdentifier": "827532f",
    "_fetchTime": 1702168251663,
    "_sourceUrl": "https://raw.githubusercontent.com/unanimated/luaegisub/master/DependencyControl.json",
    "_namespace": "ua.Selectrix"
  }
]